moira_client/__init__.py
moira_client/client.py
moira_client/moira.py
moira_client/models/__init__.py
moira_client/models/base.py
moira_client/models/config.py
moira_client/models/contact.py
moira_client/models/event.py
moira_client/models/health.py
moira_client/models/notification.py
moira_client/models/pattern.py
moira_client/models/subscription.py
moira_client/models/system_tag.py
moira_client/models/tag.py
moira_client/models/trigger.py
moira_client/models/user.py
moira_client/models/team/__init__.py
moira_client/models/team/_managers.py
moira_client/models/team/_models.py
moira_client/models/team/contact/__init__.py
moira_client/models/team/contact/_managers.py
moira_client/models/team/settings/__init__.py
moira_client/models/team/settings/_managers.py
moira_client/models/team/settings/_models.py
moira_client/models/team/subscription/__init__.py
moira_client/models/team/subscription/_managers.py
moira_client/models/team/user/__init__.py
moira_client/models/team/user/_managers.py
moira_client/models/team/user/_models.py
moira_python_client-5.1.0.dist-info/licenses/LICENSE
moira_python_client-5.1.0.dist-info/METADATA
moira_python_client-5.1.0.dist-info/WHEEL
moira_python_client-5.1.0.dist-info/top_level.txt
moira_python_client-5.1.0.dist-info/RECORD
