Metadata-Version: 2.4
Name: moira-python-client
Version: 5.1.0
Summary: Client for Moira - Alerting system based on Graphite data
Home-page: https://github.com/moira-alert/python-moira-client
Author: Alexander Lukyanchenko
Author-email: al.lukyanchenko@gmail.com
Keywords: moira monitoring client metrics alerting
Classifier: Development Status :: 4 - Beta
Classifier: Programming Language :: Python :: 3
Classifier: Programming Language :: Python :: 3.6
Classifier: Programming Language :: Python :: 3.7
Classifier: Programming Language :: Python :: 3.8
Classifier: Programming Language :: Python :: 3.9
Classifier: Operating System :: OS Independent
Classifier: Intended Audience :: Developers
Classifier: Topic :: Software Development :: Libraries
Classifier: Topic :: Utilities
Classifier: Topic :: System :: Monitoring
Classifier: License :: OSI Approved :: MIT License
License-File: LICENSE
Requires-Dist: requests>=2.4.3
Dynamic: author
Dynamic: author-email
Dynamic: classifier
Dynamic: description
Dynamic: home-page
Dynamic: keywords
Dynamic: license-file
Dynamic: requires-dist
Dynamic: summary
